[
    { "ParameterKey": "appContainerName", "ParameterValue": "f5devcentral/f5-demo-app:latest" },
    { "ParameterKey": "application", "ParameterValue": "f5app" },
    { "ParameterKey": "applicationSubnet", "ParameterValue": "" },
    { "ParameterKey": "applicationSubnets", "ParameterValue": "" },
    { "ParameterKey": "appSecurityGroupId", "ParameterValue": "OPTIONAL" },
    { "ParameterKey": "cost", "ParameterValue": "f5cost" },
    { "ParameterKey": "createAutoscaleGroup", "ParameterValue": "false" },
    { "ParameterKey": "customAppImageId", "ParameterValue": "OPTIONAL" },
    { "ParameterKey": "environment", "ParameterValue": "f5env" },
    { "ParameterKey": "group", "ParameterValue": "f5group" },
    { "ParameterKey": "instanceType", "ParameterValue": "t2.small" },
    { "ParameterKey": "owner", "ParameterValue": "f5owner" },
    { "ParameterKey": "restrictedSrcAddress", "ParameterValue": "" },
    { "ParameterKey": "scalingMaxSize", "ParameterValue": "2" },
    { "ParameterKey": "scalingMinSize", "ParameterValue": "1" },
    { "ParameterKey": "setAppPublicIp", "ParameterValue": "false" },
    { "ParameterKey": "sshKey", "ParameterValue": "" },
    { "ParameterKey": "staticIp", "ParameterValue": "" },
    { "ParameterKey": "vpc", "ParameterValue": "" }
]